uplm80/__init__.py
uplm80/ast_nodes.py
uplm80/ast_optimizer.py
uplm80/codegen.py
uplm80/compiler.py
uplm80/errors.py
uplm80/lexer.py
uplm80/parser.py
uplm80/py.typed
uplm80/runtime.py
uplm80/symbols.py
uplm80/tokens.py
uplm80-0.2.27.dist-info/licenses/LICENSE
uplm80-0.2.27.dist-info/METADATA
uplm80-0.2.27.dist-info/WHEEL
uplm80-0.2.27.dist-info/entry_points.txt
uplm80-0.2.27.dist-info/top_level.txt
uplm80-0.2.27.dist-info/RECORD
